aos_metadata_collector-2.0.1.data/scripts/metadata_collector
collector/__init__.py
collector/action_config.yml
collector/domain_config.py
collector/elasticsearch_data_collector.py
aos_metadata_collector-2.0.1.dist-info/METADATA
aos_metadata_collector-2.0.1.dist-info/WHEEL
aos_metadata_collector-2.0.1.dist-info/top_level.txt
aos_metadata_collector-2.0.1.dist-info/RECORD
