Metadata-Version: 2.1
Name: aos-metadata-collector
Version: 2.0.1
Summary: OpenSearch metadata collector for operational review
Home-page: UNKNOWN
Author: Jianwei Li
Author-email: lijianwe@amazon.com
License: UNKNOWN
Platform: UNKNOWN
Requires-Dist: requests
Requires-Dist: requests-aws4auth
Requires-Dist: boto3
Requires-Dist: pyyaml
